zag/__init__.py
zag/atom.py
zag/deciders.py
zag/exceptions.py
zag/flow.py
zag/formatters.py
zag/json.py
zag/logging.py
zag/retry.py
zag/states.py
zag/storage.py
zag/task.py
zag/test.py
zag/version.py
zag/conductors/__init__.py
zag/conductors/base.py
zag/conductors/backends/__init__.py
zag/conductors/backends/impl_blocking.py
zag/conductors/backends/impl_executor.py
zag/conductors/backends/impl_nonblocking.py
zag/contrib/__init__.py
zag/engines/__init__.py
zag/engines/base.py
zag/engines/helpers.py
zag/engines/action_engine/__init__.py
zag/engines/action_engine/builder.py
zag/engines/action_engine/compiler.py
zag/engines/action_engine/completer.py
zag/engines/action_engine/deciders.py
zag/engines/action_engine/engine.py
zag/engines/action_engine/executor.py
zag/engines/action_engine/process_executor.py
zag/engines/action_engine/runtime.py
zag/engines/action_engine/scheduler.py
zag/engines/action_engine/scopes.py
zag/engines/action_engine/selector.py
zag/engines/action_engine/traversal.py
zag/engines/action_engine/actions/__init__.py
zag/engines/action_engine/actions/base.py
zag/engines/action_engine/actions/retry.py
zag/engines/action_engine/actions/task.py
zag/engines/worker_based/__init__.py
zag/engines/worker_based/dispatcher.py
zag/engines/worker_based/endpoint.py
zag/engines/worker_based/engine.py
zag/engines/worker_based/executor.py
zag/engines/worker_based/protocol.py
zag/engines/worker_based/proxy.py
zag/engines/worker_based/server.py
zag/engines/worker_based/types.py
zag/engines/worker_based/worker.py
zag/examples/99_bottles.py
zag/examples/alphabet_soup.py
zag/examples/build_a_car.py
zag/examples/buildsystem.py
zag/examples/calculate_in_parallel.py
zag/examples/calculate_linear.py
zag/examples/create_parallel_volume.py
zag/examples/delayed_return.py
zag/examples/distance_calculator.py
zag/examples/dump_memory_backend.py
zag/examples/echo_listener.py
zag/examples/example_utils.py
zag/examples/fake_billing.py
zag/examples/graph_flow.py
zag-0.2.12.dist-info/AUTHORS
zag-0.2.12.dist-info/LICENSE
zag-0.2.12.dist-info/METADATA
zag-0.2.12.dist-info/WHEEL
zag-0.2.12.dist-info/entry_points.txt
zag-0.2.12.dist-info/pbr.json
zag-0.2.12.dist-info/top_level.txt
zag-0.2.12.dist-info/RECORD
