Metadata-Version: 2.1
Name: zag
Version: 0.2.12
Summary: Distributed workflow processing.
Home-page: https://zag.readthedocs.io
Author: Greg Hill
Author-email: jimbobhickville@gmail.com
License: UNKNOWN
Keywords: reliable,tasks,execution,parallel,dataflow,workflows,distributed
Platform: UNKNOWN
Classifier: Development Status :: 4 - Beta
Classifier: Intended Audience :: Developers
Classifier: Intended Audience :: Information Technology
Classifier: License :: OSI Approved :: Apache Software License
Classifier: Operating System :: POSIX :: Linux
Classifier: Programming Language :: Python
Classifier: Programming Language :: Python :: 2
Classifier: Programming Language :: Python :: 2.7
Classifier: Programming Language :: Python :: 3
Classifier: Programming Language :: Python :: 3.7
Classifier: Topic :: Software Development :: Libraries
Classifier: Topic :: System :: Distributed Computing
Requires-Dist: pbr (!=2.1.0,>=2.0.0)
Requires-Dist: six (>=1.10.0)
Requires-Dist: futurist (>=1.2.0)
Requires-Dist: fasteners (>=0.7.0)
Requires-Dist: networkx (>=1.10)
Requires-Dist: stevedore (>=1.20.0)
Requires-Dist: jsonschema (<4.0.0,>=2.6.0)
Requires-Dist: automaton (>=1.9.0)
Requires-Dist: oslo.utils (>=3.33.0)
Requires-Dist: oslo.serialization (!=2.19.1,>=2.18.0)
Requires-Dist: tenacity (>=4.4.0)
Requires-Dist: cachetools (>=2.0.0)
Requires-Dist: debtcollector (>=1.2.0)
Requires-Dist: stestr (>=2.0.0)
Requires-Dist: pydot (>=1.2.4)
Requires-Dist: tooz (>=1.19.0)
Requires-Dist: crontab (>=0.22.3)
Requires-Dist: contextlib2 (>=0.4.0) ; (python_version<'3.0')
Requires-Dist: enum34 (>=1.0.4) ; (python_version=='2.7' or python_version=='2.6' or python_version=='3.3')
Requires-Dist: futures (>=3.0.0) ; (python_version=='2.7' or python_version=='2.6')
Provides-Extra: database
Requires-Dist: SQLAlchemy (!=1.1.5,!=1.1.6,!=1.1.7,!=1.1.8,>=1.0.10) ; extra == 'database'
Requires-Dist: alembic (>=0.8.10) ; extra == 'database'
Requires-Dist: SQLAlchemy-Utils (>=0.30.11) ; extra == 'database'
Requires-Dist: PyMySQL (>=0.7.6) ; extra == 'database'
Requires-Dist: psycopg2 (>=2.6.2) ; extra == 'database'
Provides-Extra: eventlet
Requires-Dist: eventlet (!=0.18.3,!=0.20.1,!=0.21.0,>=0.18.2) ; extra == 'eventlet'
Provides-Extra: redis
Requires-Dist: redis (>=2.10.0) ; extra == 'redis'
Provides-Extra: test
Requires-Dist: pydotplus (>=2.0.2) ; extra == 'test'
Requires-Dist: hacking (<0.11,>=0.10.0) ; extra == 'test'
Requires-Dist: oslotest (>=3.2.0) ; extra == 'test'
Requires-Dist: mock (>=2.0.0) ; extra == 'test'
Requires-Dist: testtools (>=2.2.0) ; extra == 'test'
Requires-Dist: testscenarios (>=0.4) ; extra == 'test'
Requires-Dist: doc8 (>=0.6.0) ; extra == 'test'
Requires-Dist: sphinx (!=1.6.6,!=1.6.7,>=1.6.2) ; extra == 'test'
Provides-Extra: workers
Requires-Dist: kombu (!=4.0.2,>=4.0.0) ; extra == 'workers'
Provides-Extra: zookeeper
Requires-Dist: kazoo (>=2.2) ; extra == 'zookeeper'
Requires-Dist: zake (>=0.1.6) ; extra == 'zookeeper'
